streamsx/eventstreams/__init__.py
streamsx/eventstreams/_eventstreams.py
streamsx/eventstreams/schema.py
streamsx.eventstreams-2.0.1.dist-info/DESCRIPTION.rst
streamsx.eventstreams-2.0.1.dist-info/LICENSE.txt
streamsx.eventstreams-2.0.1.dist-info/METADATA
streamsx.eventstreams-2.0.1.dist-info/RECORD
streamsx.eventstreams-2.0.1.dist-info/WHEEL
streamsx.eventstreams-2.0.1.dist-info/metadata.json
streamsx.eventstreams-2.0.1.dist-info/top_level.txt
