Metadata-Version: 2.0
Name: streamsx.eventstreams
Version: 2.0.1
Summary: IBM Streams Event Streams integration for IBM Streams topology applications
Home-page: https://github.com/IBMStreams/pypi.streamsx.eventstreams
Author: IBM Streams @ github.com
Author-email: rolef.heinrich@de.ibm.com
License: Apache License - Version 2.0
Keywords: streams,ibmstreams,streaming,analytics,streaming-analytics,messaging,eventstreams,events
Platform: UNKNOWN
Classifier: Development Status :: 5 - Production/Stable
Classifier: License :: OSI Approved :: Apache Software License
Classifier: Programming Language :: Python :: 3
Classifier: Programming Language :: Python :: 3.5
Classifier: Programming Language :: Python :: 3.6
Classifier: Programming Language :: Python :: 3.7
Requires-Dist: streamsx (>=1.12.10)
Requires-Dist: streamsx.toolkits
